global_forecasting_system/__init__.py
global_forecasting_system/constants.py
global_forecasting_system/global_forecasting_system.py
global_forecasting_system-1.2.1.dist-info/licenses/LICENSE
global_forecasting_system-1.2.1.dist-info/METADATA
global_forecasting_system-1.2.1.dist-info/WHEEL
global_forecasting_system-1.2.1.dist-info/top_level.txt
global_forecasting_system-1.2.1.dist-info/RECORD
